neuropod-0.2.0.data/purelib/neuropod/__init__.py
neuropod-0.2.0.data/purelib/neuropod/libneuropod.so
neuropod-0.2.0.data/purelib/neuropod/loader.py
neuropod-0.2.0.data/purelib/neuropod/neuropod_multiprocess_worker
neuropod-0.2.0.data/purelib/neuropod/neuropod_native.so
neuropod-0.2.0.data/purelib/neuropod/packagers.py
neuropod-0.2.0.data/purelib/neuropod/registry.py
neuropod-0.2.0.data/purelib/neuropod/backends/__init__.py
neuropod-0.2.0.data/purelib/neuropod/backends/config_utils.py
neuropod-0.2.0.data/purelib/neuropod/backends/neuropod_executor.py
neuropod-0.2.0.data/purelib/neuropod/backends/keras/__init__.py
neuropod-0.2.0.data/purelib/neuropod/backends/keras/packager.py
neuropod-0.2.0.data/purelib/neuropod/backends/python/__init__.py
neuropod-0.2.0.data/purelib/neuropod/backends/python/executor.py
neuropod-0.2.0.data/purelib/neuropod/backends/python/packager.py
neuropod-0.2.0.data/purelib/neuropod/backends/pytorch/__init__.py
neuropod-0.2.0.data/purelib/neuropod/backends/pytorch/packager.py
neuropod-0.2.0.data/purelib/neuropod/backends/tensorflow/__init__.py
neuropod-0.2.0.data/purelib/neuropod/backends/tensorflow/executor.py
neuropod-0.2.0.data/purelib/neuropod/backends/tensorflow/packager.py
neuropod-0.2.0.data/purelib/neuropod/backends/torchscript/__init__.py
neuropod-0.2.0.data/purelib/neuropod/backends/torchscript/executor.py
neuropod-0.2.0.data/purelib/neuropod/backends/torchscript/packager.py
neuropod-0.2.0.data/purelib/neuropod/tests/__init__.py
neuropod-0.2.0.data/purelib/neuropod/tests/gpu_test_basic_environment_support.py
neuropod-0.2.0.data/purelib/neuropod/tests/gpu_test_torchscript_devices.py
neuropod-0.2.0.data/purelib/neuropod/tests/test_config_utils.py
neuropod-0.2.0.data/purelib/neuropod/tests/test_eval_utils.py
neuropod-0.2.0.data/purelib/neuropod/tests/test_keras_packaging.py
neuropod-0.2.0.data/purelib/neuropod/tests/test_python_isolation.py
neuropod-0.2.0.data/purelib/neuropod/tests/test_pytorch_packaging.py
neuropod-0.2.0.dist-info/METADATA
neuropod-0.2.0.dist-info/WHEEL
neuropod-0.2.0.dist-info/top_level.txt
neuropod-0.2.0.dist-info/RECORD
