Metadata-Version: 2.1
Name: neuropod
Version: 0.2.0
Summary: UNKNOWN
Home-page: UNKNOWN
Author: UNKNOWN
Author-email: UNKNOWN
License: UNKNOWN
Platform: UNKNOWN
Requires-Dist: numpy
Requires-Dist: testpath
Requires-Dist: typing
Requires-Dist: future
Requires-Dist: six
